API_libs-0.1.16.dist-info/DESCRIPTION.rst
API_libs-0.1.16.dist-info/METADATA
API_libs-0.1.16.dist-info/RECORD
API_libs-0.1.16.dist-info/WHEEL
API_libs-0.1.16.dist-info/metadata.json
API_libs-0.1.16.dist-info/top_level.txt
api_libs/__init__.py
api_libs/interface.py
api_libs/route.py
api_libs/adapters/__init__.py
api_libs/adapters/tornado_adapter.py
api_libs/parameters/Arguments.py
api_libs/parameters/Parameter.py
api_libs/parameters/__init__.py
api_libs/parameters/bool_param.py
api_libs/parameters/dict_param.py
api_libs/parameters/list_param.py
api_libs/parameters/number_param.py
api_libs/parameters/object_param.py
api_libs/parameters/str_param.py
api_libs/parameters/time_param.py
api_libs/parameters/two_step_param.py
api_libs/parameters/utils.py
