Metadata-Version: 2.0
Name: API-libs
Version: 0.1.16
Summary: 一套灵活的组件，帮助你快速搭建起一个 API 系统
Home-page: https://github.com/anjianshi/api-libs
Author: anjianshi
Author-email: anjianshi@gmail.com
License: MIT
Keywords: api,tornado
Platform: any
Classifier: Intended Audience :: Developers
Classifier: License :: OSI Approved :: MIT License
Classifier: Operating System :: OS Independent
Classifier: Programming Language :: Python
Classifier: Programming Language :: Python :: 3.5
